spectrumCatcher/__init__.py
spectrumCatcher/downloader.py
spectrumCatcher/processor.py
spectrumCatcher/some_function.py
spectrumCathcer-0.1.0.dist-info/METADATA
spectrumCathcer-0.1.0.dist-info/WHEEL
spectrumCathcer-0.1.0.dist-info/top_level.txt
spectrumCathcer-0.1.0.dist-info/RECORD
